torch_featurelayer/__init__.py
torch_featurelayer/_rgetattr.py
torch_featurelayer/feature_layer.py
torch_featurelayer/feature_layers.py
torch_featurelayer/layer_candidates.py
torch_featurelayer-0.1.2.dist-info/LICENSE
torch_featurelayer-0.1.2.dist-info/METADATA
torch_featurelayer-0.1.2.dist-info/WHEEL
torch_featurelayer-0.1.2.dist-info/top_level.txt
torch_featurelayer-0.1.2.dist-info/RECORD
