Metadata-Version: 2.1
Name: torch-featurelayer
Version: 0.1.2
Summary: Useful utility functions and wrappers for hooking onto layers within PyTorch models for feature extraction.
Author-email: spencerwooo <spencer.woo@outlook.com>
License: MIT License
Project-URL: Repository, https://github.com/spencerwooo/torch-featurelayer
Project-URL: Documentation, https://github.com/spencerwooo/torch-featurelayer/blob/main/README.md
Keywords: torch,pytorch,torchvision,feature-extraction
Classifier: Development Status :: 5 - Production/Stable
Classifier: Environment :: GPU :: NVIDIA CUDA
Classifier: Intended Audience :: Developers
Classifier: License :: OSI Approved :: MIT License
Classifier: Operating System :: OS Independent
Classifier: Programming Language :: Python :: 3.10
Classifier: Programming Language :: Python :: 3.11
Classifier: Programming Language :: Python :: 3.12
Classifier: Programming Language :: Python :: 3 :: Only
Classifier: Topic :: Software Development :: Libraries :: Python Modules
Requires-Python: >=3.10
License-File: LICENSE
Requires-Dist: torch
Provides-Extra: dev
Requires-Dist: mypy ; extra == 'dev'
Requires-Dist: ruff ; extra == 'dev'
Provides-Extra: test
Requires-Dist: torchvision <0.18,>=0.15 ; extra == 'test'
Requires-Dist: pytest ; extra == 'test'
